brainus_ai/__init__.py
brainus_ai/client.py
brainus_ai/exceptions.py
brainus_ai/models.py
brainus_ai/py.typed
brainus_ai-0.1.6.dist-info/METADATA
brainus_ai-0.1.6.dist-info/WHEEL
brainus_ai-0.1.6.dist-info/RECORD
